statr.cpython-36m-x86_64-linux-gnu.so
statr/__init__.py
statr/cstatr.pxd
statr/statr.bycython.c
statr/statr.c
statr/statr.pyx
statr-0.1.0.dev6.dist-info/DESCRIPTION.rst
statr-0.1.0.dev6.dist-info/METADATA
statr-0.1.0.dev6.dist-info/RECORD
statr-0.1.0.dev6.dist-info/WHEEL
statr-0.1.0.dev6.dist-info/metadata.json
statr-0.1.0.dev6.dist-info/top_level.txt
