Metadata-Version: 2.0
Name: statr
Version: 0.1.0.dev6
Summary: Trustworthy statistics in Python
Home-page: https://github.com/franiis/statr-python
Author: Piotr Krzeszewski
Author-email: krzeszewskipiotr@gmail.com
License: GPLv3
Project-URL: Bug Reports, https://github.com/franiis/statr-python/issues/
Project-URL: Source, https://github.com/franiis/statr-python/
Keywords: statr r statistics
Platform: UNKNOWN
Classifier: Development Status :: 3 - Alpha
Classifier: License :: OSI Approved :: GNU General Public License v3 or later (GPLv3+)
Classifier: Intended Audience :: Science/Research
Classifier: Natural Language :: English
Classifier: Topic :: Scientific/Engineering :: Mathematics
Requires-Python: >=3, <4
Requires-Dist: numpy (>=1.14)
